{
  "account_address": "0xbf2c878cd5d6043697b32067be141647deeb097c",
  "account_label": "Distant-Prairie",
  "account_name_meta": {
    "pseudonym": "Distant-Prairie",
    "name": "cyc0lin4",
    "account_name": "account_39"
  },
  "analysis_window": "2026-03-12 15:41:47 UTC -> 2026-04-11 11:58:35 UTC",
  "trade_rows_used": 485,
  "total_buy_usdc": 317985.364041,
  "total_sell_usdc": 65034.426781,
  "api_summary": {
    "positions_value": 149.6141,
    "traded_markets": 330
  },
  "metrics": {
    "dual_side_condition_count_ratio": 0.0,
    "dual_side_buy_usdc_ratio": 0.0,
    "dual_side_buy_usdc_ratio_1h": 0.0,
    "token_fast_20m_count": 14,
    "token_fast_20m_buy_usdc_ratio": 0.003532,
    "token_fast_20m_sell_usdc_ratio": 0.013233,
    "noncopyable_token_fast_buy_ratio": 0.002839,
    "noncopyable_token_fast_sell_ratio": 0.013233,
    "noncopyable_token_fast_token_ratio": 0.055556,
    "event_rebalance_20m_count": 0,
    "event_rebalance_20m_buy_ratio": 0.0,
    "event_rebalance_20m_sell_ratio": 0.0,
    "event_rebalance_20m_event_ratio": 0.0,
    "exclusive_multi_market_buy_ratio": 0.0,
    "nested_deadline_multi_market_buy_ratio": 0.0,
    "independent_multi_market_buy_ratio": 0.0,
    "unknown_multi_market_buy_ratio": 0.0,
    "exclusive_concurrent_leg_ratio": 0.0,
    "nested_concurrent_leg_ratio": 0.0,
    "exclusive_overlap_time_ratio": 0.0,
    "nested_overlap_time_ratio": 0.0,
    "weighted_multi_market_risk_ratio": 0.0,
    "exclusive_sequential_switch_count": 0,
    "nested_sequential_roll_count": 0,
    "clean_event_count": 35,
    "semiclean_event_count": 0,
    "dirty_event_count": 1,
    "deployable_event_equivalent": 35.0,
    "deployable_event_density": 1.172726,
    "top1_event_buy_ratio": 0.073839,
    "top3_event_buy_ratio": 0.175288,
    "median_holding_time_sec": 25480.0,
    "weighted_median_holding_time_sec": 35960,
    "sell_usdc_ratio_within_20m": 7.6e-05,
    "sell_usdc_ratio_within_1h": 0.014414,
    "trade_count": 485.0,
    "active_trading_days": 14.0,
    "window_days": 30.845,
    "active_day_ratio": 0.453882,
    "avg_trades_per_active_day": 34.642857
  },
  "event_records": [
    {
      "eventSlug": "nba-bkn-atl-2026-03-12",
      "relation_type": "single_market",
      "event_subtype": "single_leg",
      "classification": "clean",
      "distinct_conditions": 1,
      "event_buy_usdc": 7846.866374,
      "concurrent_buy_usdc": 0.0,
      "concurrent_ratio": 0.0,
      "overlap_time_ratio": 0.0,
      "max_concurrent_legs": 1,
      "sequential_switch_count": 0
    },
    {
      "eventSlug": "nba-chi-lac-2026-03-13",
      "relation_type": "single_market",
      "event_subtype": "single_leg",
      "classification": "clean",
      "distinct_conditions": 1,
      "event_buy_usdc": 10319.951069,
      "concurrent_buy_usdc": 0.0,
      "concurrent_ratio": 0.0,
      "overlap_time_ratio": 0.0,
      "max_concurrent_legs": 1,
      "sequential_switch_count": 0
    },
    {
      "eventSlug": "nba-uta-por-2026-03-13",
      "relation_type": "single_market",
      "event_subtype": "single_leg",
      "classification": "clean",
      "distinct_conditions": 1,
      "event_buy_usdc": 10679.985525,
      "concurrent_buy_usdc": 0.0,
      "concurrent_ratio": 0.0,
      "overlap_time_ratio": 0.0,
      "max_concurrent_legs": 1,
      "sequential_switch_count": 0
    },
    {
      "eventSlug": "nba-cle-dal-2026-03-13",
      "relation_type": "single_market",
      "event_subtype": "single_leg",
      "classification": "clean",
      "distinct_conditions": 1,
      "event_buy_usdc": 9349.88006,
      "concurrent_buy_usdc": 0.0,
      "concurrent_ratio": 0.0,
      "overlap_time_ratio": 0.0,
      "max_concurrent_legs": 1,
      "sequential_switch_count": 0
    },
    {
      "eventSlug": "nba-bkn-phi-2026-03-14",
      "relation_type": "single_market",
      "event_subtype": "single_leg",
      "classification": "clean",
      "distinct_conditions": 1,
      "event_buy_usdc": 9240.0,
      "concurrent_buy_usdc": 0.0,
      "concurrent_ratio": 0.0,
      "overlap_time_ratio": 0.0,
      "max_concurrent_legs": 1,
      "sequential_switch_count": 0
    },
    {
      "eventSlug": "nba-mil-atl-2026-03-14",
      "relation_type": "single_market",
      "event_subtype": "single_leg",
      "classification": "clean",
      "distinct_conditions": 1,
      "event_buy_usdc": 7198.088148,
      "concurrent_buy_usdc": 0.0,
      "concurrent_ratio": 0.0,
      "overlap_time_ratio": 0.0,
      "max_concurrent_legs": 1,
      "sequential_switch_count": 0
    },
    {
      "eventSlug": "nba-sac-lac-2026-03-14",
      "relation_type": "single_market",
      "event_subtype": "single_leg",
      "classification": "clean",
      "distinct_conditions": 1,
      "event_buy_usdc": 10439.948464,
      "concurrent_buy_usdc": 0.0,
      "concurrent_ratio": 0.0,
      "overlap_time_ratio": 0.0,
      "max_concurrent_legs": 1,
      "sequential_switch_count": 0
    },
    {
      "eventSlug": "nba-gsw-nyk-2026-03-15",
      "relation_type": "single_market",
      "event_subtype": "single_leg",
      "classification": "clean",
      "distinct_conditions": 1,
      "event_buy_usdc": 11439.970664,
      "concurrent_buy_usdc": 0.0,
      "concurrent_ratio": 0.0,
      "overlap_time_ratio": 0.0,
      "max_concurrent_legs": 1,
      "sequential_switch_count": 0
    },
    {
      "eventSlug": "nba-dal-cle-2026-03-15",
      "relation_type": "single_market",
      "event_subtype": "single_leg",
      "classification": "clean",
      "distinct_conditions": 1,
      "event_buy_usdc": 11676.024614,
      "concurrent_buy_usdc": 0.0,
      "concurrent_ratio": 0.0,
      "overlap_time_ratio": 0.0,
      "max_concurrent_legs": 1,
      "sequential_switch_count": 0
    },
    {
      "eventSlug": "nba-phx-bos-2026-03-16",
      "relation_type": "single_market",
      "event_subtype": "single_leg",
      "classification": "clean",
      "distinct_conditions": 1,
      "event_buy_usdc": 11049.201707,
      "concurrent_buy_usdc": 0.0,
      "concurrent_ratio": 0.0,
      "overlap_time_ratio": 0.0,
      "max_concurrent_legs": 1,
      "sequential_switch_count": 0
    },
    {
      "eventSlug": "nba-mem-chi-2026-03-16",
      "relation_type": "single_market",
      "event_subtype": "single_leg",
      "classification": "clean",
      "distinct_conditions": 1,
      "event_buy_usdc": 4140.0,
      "concurrent_buy_usdc": 0.0,
      "concurrent_ratio": 0.0,
      "overlap_time_ratio": 0.0,
      "max_concurrent_legs": 1,
      "sequential_switch_count": 0
    },
    {
      "eventSlug": "nba-gsw-was-2026-03-16",
      "relation_type": "single_market",
      "event_subtype": "single_leg",
      "classification": "clean",
      "distinct_conditions": 1,
      "event_buy_usdc": 11136.998861,
      "concurrent_buy_usdc": 0.0,
      "concurrent_ratio": 0.0,
      "overlap_time_ratio": 0.0,
      "max_concurrent_legs": 1,
      "sequential_switch_count": 0
    },
    {
      "eventSlug": "nba-ind-nyk-2026-03-17",
      "relation_type": "single_market",
      "event_subtype": "single_leg",
      "classification": "clean",
      "distinct_conditions": 1,
      "event_buy_usdc": 5445.0,
      "concurrent_buy_usdc": 0.0,
      "concurrent_ratio": 0.0,
      "overlap_time_ratio": 0.0,
      "max_concurrent_legs": 1,
      "sequential_switch_count": 0
    },
    {
      "eventSlug": "nba-okc-orl-2026-03-17",
      "relation_type": "single_market",
      "event_subtype": "single_leg",
      "classification": "clean",
      "distinct_conditions": 1,
      "event_buy_usdc": 12040.0,
      "concurrent_buy_usdc": 0.0,
      "concurrent_ratio": 0.0,
      "overlap_time_ratio": 0.0,
      "max_concurrent_legs": 1,
      "sequential_switch_count": 0
    },
    {
      "eventSlug": "nba-cle-mil-2026-03-17",
      "relation_type": "single_market",
      "event_subtype": "single_leg",
      "classification": "clean",
      "distinct_conditions": 1,
      "event_buy_usdc": 12000.0,
      "concurrent_buy_usdc": 0.0,
      "concurrent_ratio": 0.0,
      "overlap_time_ratio": 0.0,
      "max_concurrent_legs": 1,
      "sequential_switch_count": 0
    },
    {
      "eventSlug": "cbb-sfaus-tulsa-2026-03-17",
      "relation_type": "single_market",
      "event_subtype": "single_leg",
      "classification": "clean",
      "distinct_conditions": 1,
      "event_buy_usdc": 21.6,
      "concurrent_buy_usdc": 0.0,
      "concurrent_ratio": 0.0,
      "overlap_time_ratio": 0.0,
      "max_concurrent_legs": 1,
      "sequential_switch_count": 0
    },
    {
      "eventSlug": "nba-gsw-bos-2026-03-18",
      "relation_type": "single_market",
      "event_subtype": "single_leg",
      "classification": "clean",
      "distinct_conditions": 1,
      "event_buy_usdc": 12750.0,
      "concurrent_buy_usdc": 0.0,
      "concurrent_ratio": 0.0,
      "overlap_time_ratio": 0.0,
      "max_concurrent_legs": 1,
      "sequential_switch_count": 0
    },
    {
      "eventSlug": "nba-por-ind-2026-03-18",
      "relation_type": "single_market",
      "event_subtype": "single_leg",
      "classification": "clean",
      "distinct_conditions": 1,
      "event_buy_usdc": 12471.3582,
      "concurrent_buy_usdc": 0.0,
      "concurrent_ratio": 0.0,
      "overlap_time_ratio": 0.0,
      "max_concurrent_legs": 1,
      "sequential_switch_count": 0
    },
    {
      "eventSlug": "nba-atl-dal-2026-03-18",
      "relation_type": "single_market",
      "event_subtype": "single_leg",
      "classification": "clean",
      "distinct_conditions": 1,
      "event_buy_usdc": 4560.0,
      "concurrent_buy_usdc": 0.0,
      "concurrent_ratio": 0.0,
      "overlap_time_ratio": 0.0,
      "max_concurrent_legs": 1,
      "sequential_switch_count": 0
    },
    {
      "eventSlug": "will-the-us-invade-cuba-in-2026",
      "relation_type": "single_market",
      "event_subtype": "single_leg",
      "classification": "clean",
      "distinct_conditions": 1,
      "event_buy_usdc": 740.0,
      "concurrent_buy_usdc": 0.0,
      "concurrent_ratio": 0.0,
      "overlap_time_ratio": 0.0,
      "max_concurrent_legs": 1,
      "sequential_switch_count": 0
    },
    {
      "eventSlug": "us-forces-enter-iran-by",
      "relation_type": "single_market",
      "event_subtype": "single_leg",
      "classification": "dirty",
      "distinct_conditions": 1,
      "event_buy_usdc": 1834.975664,
      "concurrent_buy_usdc": 0.0,
      "concurrent_ratio": 0.0,
      "overlap_time_ratio": 0.0,
      "max_concurrent_legs": 1,
      "sequential_switch_count": 0
    },
    {
      "eventSlug": "nba-cle-chi-2026-03-19",
      "relation_type": "single_market",
      "event_subtype": "single_leg",
      "classification": "clean",
      "distinct_conditions": 1,
      "event_buy_usdc": 12899.97297,
      "concurrent_buy_usdc": 0.0,
      "concurrent_ratio": 0.0,
      "overlap_time_ratio": 0.0,
      "max_concurrent_legs": 1,
      "sequential_switch_count": 0
    },
    {
      "eventSlug": "nba-phx-sas-2026-03-19",
      "relation_type": "single_market",
      "event_subtype": "single_leg",
      "classification": "clean",
      "distinct_conditions": 1,
      "event_buy_usdc": 12000.0,
      "concurrent_buy_usdc": 0.0,
      "concurrent_ratio": 0.0,
      "overlap_time_ratio": 0.0,
      "max_concurrent_legs": 1,
      "sequential_switch_count": 0
    },
    {
      "eventSlug": "nba-orl-cha-2026-03-19",
      "relation_type": "single_market",
      "event_subtype": "single_leg",
      "classification": "clean",
      "distinct_conditions": 1,
      "event_buy_usdc": 3333.0,
      "concurrent_buy_usdc": 0.0,
      "concurrent_ratio": 0.0,
      "overlap_time_ratio": 0.0,
      "max_concurrent_legs": 1,
      "sequential_switch_count": 0
    },
    {
      "eventSlug": "nba-bos-mem-2026-03-20",
      "relation_type": "single_market",
      "event_subtype": "single_leg",
      "classification": "clean",
      "distinct_conditions": 1,
      "event_buy_usdc": 16200.0,
      "concurrent_buy_usdc": 0.0,
      "concurrent_ratio": 0.0,
      "overlap_time_ratio": 0.0,
      "max_concurrent_legs": 1,
      "sequential_switch_count": 0
    },
    {
      "eventSlug": "nba-gsw-det-2026-03-20",
      "relation_type": "single_market",
      "event_subtype": "single_leg",
      "classification": "clean",
      "distinct_conditions": 1,
      "event_buy_usdc": 10686.5,
      "concurrent_buy_usdc": 0.0,
      "concurrent_ratio": 0.0,
      "overlap_time_ratio": 0.0,
      "max_concurrent_legs": 1,
      "sequential_switch_count": 0
    },
    {
      "eventSlug": "bun-bay-uni-2026-03-21",
      "relation_type": "single_market",
      "event_subtype": "single_leg",
      "classification": "clean",
      "distinct_conditions": 1,
      "event_buy_usdc": 23479.7776,
      "concurrent_buy_usdc": 0.0,
      "concurrent_ratio": 0.0,
      "overlap_time_ratio": 0.0,
      "max_concurrent_legs": 1,
      "sequential_switch_count": 0
    },
    {
      "eventSlug": "nba-mil-phx-2026-03-21",
      "relation_type": "single_market",
      "event_subtype": "single_leg",
      "classification": "clean",
      "distinct_conditions": 1,
      "event_buy_usdc": 11609.64,
      "concurrent_buy_usdc": 0.0,
      "concurrent_ratio": 0.0,
      "overlap_time_ratio": 0.0,
      "max_concurrent_legs": 1,
      "sequential_switch_count": 0
    },
    {
      "eventSlug": "nba-gsw-atl-2026-03-21",
      "relation_type": "single_market",
      "event_subtype": "single_leg",
      "classification": "clean",
      "distinct_conditions": 1,
      "event_buy_usdc": 16059.225593,
      "concurrent_buy_usdc": 0.0,
      "concurrent_ratio": 0.0,
      "overlap_time_ratio": 0.0,
      "max_concurrent_legs": 1,
      "sequential_switch_count": 0
    },
    {
      "eventSlug": "lal-bar-ray-2026-03-22",
      "relation_type": "single_market",
      "event_subtype": "single_leg",
      "classification": "clean",
      "distinct_conditions": 1,
      "event_buy_usdc": 11160.0,
      "concurrent_buy_usdc": 0.0,
      "concurrent_ratio": 0.0,
      "overlap_time_ratio": 0.0,
      "max_concurrent_legs": 1,
      "sequential_switch_count": 0
    },
    {
      "eventSlug": "nba-mem-atl-2026-03-23",
      "relation_type": "single_market",
      "event_subtype": "single_leg",
      "classification": "clean",
      "distinct_conditions": 1,
      "event_buy_usdc": 6160.0,
      "concurrent_buy_usdc": 0.0,
      "concurrent_ratio": 0.0,
      "overlap_time_ratio": 0.0,
      "max_concurrent_legs": 1,
      "sequential_switch_count": 0
    },
    {
      "eventSlug": "nba-hou-chi-2026-03-23",
      "relation_type": "single_market",
      "event_subtype": "single_leg",
      "classification": "clean",
      "distinct_conditions": 1,
      "event_buy_usdc": 5687.728528,
      "concurrent_buy_usdc": 0.0,
      "concurrent_ratio": 0.0,
      "overlap_time_ratio": 0.0,
      "max_concurrent_legs": 1,
      "sequential_switch_count": 0
    },
    {
      "eventSlug": "nba-tor-uta-2026-03-23",
      "relation_type": "single_market",
      "event_subtype": "single_leg",
      "classification": "clean",
      "distinct_conditions": 1,
      "event_buy_usdc": 2408.0,
      "concurrent_buy_usdc": 0.0,
      "concurrent_ratio": 0.0,
      "overlap_time_ratio": 0.0,
      "max_concurrent_legs": 1,
      "sequential_switch_count": 0
    },
    {
      "eventSlug": "nba-nop-nyk-2026-03-24",
      "relation_type": "single_market",
      "event_subtype": "single_leg",
      "classification": "clean",
      "distinct_conditions": 1,
      "event_buy_usdc": 9856.0,
      "concurrent_buy_usdc": 0.0,
      "concurrent_ratio": 0.0,
      "overlap_time_ratio": 0.0,
      "max_concurrent_legs": 1,
      "sequential_switch_count": 0
    },
    {
      "eventSlug": "nba-mil-phi-2026-04-12",
      "relation_type": "single_market",
      "event_subtype": "single_leg",
      "classification": "clean",
      "distinct_conditions": 1,
      "event_buy_usdc": 32.55,
      "concurrent_buy_usdc": 0.0,
      "concurrent_ratio": 0.0,
      "overlap_time_ratio": 0.0,
      "max_concurrent_legs": 1,
      "sequential_switch_count": 0
    },
    {
      "eventSlug": "nba-was-cle-2026-04-12",
      "relation_type": "single_market",
      "event_subtype": "single_leg",
      "classification": "clean",
      "distinct_conditions": 1,
      "event_buy_usdc": 33.12,
      "concurrent_buy_usdc": 0.0,
      "concurrent_ratio": 0.0,
      "overlap_time_ratio": 0.0,
      "max_concurrent_legs": 1,
      "sequential_switch_count": 0
    }
  ],
  "token_fast_candidates_count": 14,
  "noncopyable_token_fast_count": 9,
  "score_breakdown": {
    "copyability_score": 34.92,
    "deployability_score": 20,
    "multi_market_structure_score": 20,
    "pnl_curve_stability_score": 8.33,
    "pnl_confidence": 0.75,
    "pnl_windows_available": 2,
    "risk_penalty_adjustment": 0,
    "concentration_penalty": 0.0,
    "low_frequency_cap": null,
    "active_trading_days": 14.0,
    "trade_count": 485.0,
    "active_day_ratio": 0.453882,
    "avg_trades_per_active_day": 34.642857,
    "raw_before_cap": 83.25,
    "pnl_tag": "long_strong_recent_weak",
    "decision_score_basis": "calibrated_anchor_score",
    "anchor_offset": -23.32,
    "anchor_target_score": 60.0,
    "anchor_calibration_scale": 0.65,
    "anchor_enabled": true,
    "caution_risk_gate_triggered": false,
    "severe_risk_gate_triggered": false
  },
  "raw_score": 83.25,
  "anchored_score": 59.95,
  "delta_vs_anchor_60": -0.05,
  "delta_vs_anchor_raw": -0.07,
  "final_score": 59.95,
  "decision": "selective_copying_only",
  "anchor_context": {
    "anchor_enabled": true,
    "anchor_version": "anchor_v2_20260411",
    "anchor_account": "0x39d0f1dca6fb7e5514858c1a337724a426764fe8",
    "anchor_target_score": 60.0,
    "anchor_offset": -23.32,
    "anchor_raw_base_score": 83.32,
    "anchor_calibration_scale": 0.65
  },
  "pnl_curve": {
    "all_time": {
      "window": "all_time",
      "shape": "smooth_up",
      "score": 12,
      "points_count": 136,
      "total_return": 74595.273137,
      "trend_slope": 425.78961,
      "max_drawdown": 19645.956832,
      "daily_volatility": 3059.486389
    },
    "d30": {
      "window": "d30",
      "shape": "down",
      "score": -6,
      "points_count": 8,
      "total_return": 2908.39932,
      "trend_slope": -745.096947,
      "max_drawdown": 15225.368521,
      "daily_volatility": 6382.173791
    },
    "d7": {
      "window": "d7",
      "shape": "insufficient_data",
      "score": 0,
      "points_count": 1,
      "total_return": 0.0,
      "trend_slope": 0.0,
      "max_drawdown": 0.0,
      "daily_volatility": 0.0
    },
    "summary_tag": "long_strong_recent_weak"
  },
  "keyword_profile": {
    "sector_tags": [
      "sports",
      "geopolitics"
    ],
    "whitelist_keywords": [
      "warriors",
      "cavaliers",
      "hawks",
      "celtics",
      "suns",
      "win",
      "bulls",
      "bucks",
      "knicks",
      "grizzlies",
      "mavericks",
      "nchen"
    ],
    "hard_blacklist_keywords": [],
    "soft_blacklist_keywords": [],
    "whitelist_keyword_count": 31,
    "hard_blacklist_keyword_count": 0,
    "soft_blacklist_keyword_count": 0
  },
  "behavior_summary": {
    "behavior_points": [
      "Observed 485 trades across 14 active trading days in the analysis window.",
      "PnL curve shapes: all-time=smooth_up, 30d=down, 7d=insufficient_data.",
      "Dominant sector themes: sports, geopolitics."
    ],
    "strength_points": [
      "Low dual-side condition exposure, indicating cleaner directional expression.",
      "Low non-copyable token-fast BUY ratio.",
      "Nested concurrent behavior remains relatively contained.",
      "Weighted multi-market structure risk is controlled.",
      "Topic supply is broad enough for selective deployment.",
      "All-time PnL profile is smooth-up, supporting strategy consistency.",
      "Operational whitelist themes: warriors, cavaliers, hawks, celtics, suns, win."
    ],
    "risk_points": [
      "Recent 30-day PnL is down, which weakens near-term copy confidence."
    ]
  },
  "narrative_conclusion": "Calibrated decision score is 59.95 (anchor-referenced), decision: selective_copying_only. Primary sector exposure: sports, geopolitics. Strengths: good deployable event breadth, contained weighted multi-market risk, low non-copyable token-fast ratio. Whitelist themes (higher priority for selective following): warriors, cavaliers, hawks, celtics, suns. PnL curve tag: long_strong_recent_weak. This account is best used in selective-copy mode: copy whitelist themes and block blacklist themes.",
  "assumptions": [],
  "generated_at_utc": "2026-04-19T16:51:13.569556+00:00"
}